[
  {
    "content_id": 716012,
    "reference_id": 8976,
    "title": "Colossenses 1.1",
    "media_type": "Text",
    "index_reference": "51001001",
    "language": "por",
    "content": "<p>Timóteo foi um dos colaboradores mais próximos de Paulo. O relacionamento deles era muito forte. O trabalho de Timóteo foi tão importante que Paulo o incluiu como remetente desta carta. Ele também o incluiu em 2 Coríntios, Filipenses, 1 e 2 Tessalonicenses e Filemom.</p>",
    "associations": {
      "passage": [
        {
          "start_ref": "51001001",
          "start_ref_usfm": "COL 1:1",
          "end_ref": "51001001",
          "end_ref_usfm": "COL 1:1"
        }
      ],
      "resource": []
    }
  },
  {
    "content_id": 716021,
    "reference_id": 8985,
    "title": "Colossenses 1.2",
    "media_type": "Text",
    "index_reference": "51001002",
    "language": "por",
    "content": "<ul><li><p>Colossos estava no vale do rio Lico, no oeste da Ásia Menor. Ficava cerca de 193 quilômetros (120 milhas) a leste de Éfeso e 16 quilômetros (10 milhas) a sudeste de Laodiceia. Sua localização em uma importante estrada romana o expunha às tendências sociais e religiosas da época.</p></li><li><p><em>Irmãos</em>: Grego <em>adelphoi</em>, um termo usado para se referir a membros da família, tanto homens quanto mulheres.</p></li></ul>",
    "associations": {
      "passage": [
        {
          "start_ref": "51001002",
          "start_ref_usfm": "COL 1:2",
          "end_ref": "51001002",
          "end_ref_usfm": "COL 1:2"
        }
      ],
      "resource": []
    }
  },
  {
    "content_id": 716022,
    "reference_id": 8986,
    "title": "Colossenses 1.3–14",
    "media_type": "Text",
    "index_reference": "51001003-51001014",
    "language": "por",
    "content": "<p>Esta seção começa com uma ação de graças, comum nas cartas do Novo Testamento. Paulo agradece a Deus pelo crescimento da fé dos colossenses e ora para que eles compreendam ainda mais. Através desta oração, Paulo demonstra sua preocupação com a influência de falsos mestres.</p>",
    "associations": {
      "passage": [
        {
          "start_ref": "51001003",
          "start_ref_usfm": "COL 1:3",
          "end_ref": "51001014",
          "end_ref_usfm": "COL 1:14"
        }
      ],
      "resource": []
    }
  },
  {
    "content_id": 716023,
    "reference_id": 8987,
    "title": "Colossenses 1.4",
    "media_type": "Text",
    "index_reference": "51001004",
    "language": "por",
    "content": "<p><em>Todos os santos</em> (significando <em>santos</em>): O Novo Testamento chama todos os cristãos de <em>santos</em>. Eles são separados por Deus como Seu povo santo (<a href=\"https://ref.ly/Col3:12\">3.12</a>).</p>",
    "associations": {
      "passage": [
        {
          "start_ref": "51001004",
          "start_ref_usfm": "COL 1:4",
          "end_ref": "51001004",
          "end_ref_usfm": "COL 1:4"
        }
      ],
      "resource": []
    }
  },
  {
    "content_id": 716024,
    "reference_id": 8988,
    "title": "Colossenses 1.5",
    "media_type": "Text",
    "index_reference": "51001005",
    "language": "por",
    "content": "<p>A esperança confiante dos cristãos colossenses lhes proporciona uma base segura para sua fé e amor (<a href=\"https://ref.ly/Col1:4\">1.4</a>). • O que Deus reservou para os crentes ainda não foi totalmente revelado, mas já existe no céu.</p>",
    "associations": {
      "passage": [
        {
          "start_ref": "51001005",
          "start_ref_usfm": "COL 1:5",
          "end_ref": "51001005",
          "end_ref_usfm": "COL 1:5"
        }
      ],
      "resource": []
    }
  },
  {
    "content_id": 716025,
    "reference_id": 8989,
    "title": "Colossenses 1.6",
    "media_type": "Text",
    "index_reference": "51001006",
    "language": "por",
    "content": "<p>dando frutos em todos os lugares ao transformar vidas: As boas-novas são eficazes para transformar vidas e promover o crescimento espiritual (cp. <a href=\"https://ref.ly/Col1:10\">1.10</a>).</p>",
    "associations": {
      "passage": [
        {
          "start_ref": "51001006",
          "start_ref_usfm": "COL 1:6",
          "end_ref": "51001006",
          "end_ref_usfm": "COL 1:6"
        }
      ],
      "resource": []
    }
  },
  {
    "content_id": 716026,
    "reference_id": 8990,
    "title": "Colossenses 1.7",
    "media_type": "Text",
    "index_reference": "51001007",
    "language": "por",
    "content": "<p>Epafras (veja também <a href=\"https://ref.ly/Col4:12-Col4:13\">4.12–13</a>; <a href=\"https://ref.ly/Phlm1:23\">Fm 1.23</a>) provavelmente se converteu quando Paulo ministrou em Éfeso (veja <a href=\"https://ref.ly/Acts19:10\">At 19.10</a>) e depois voltou para Colossos para levar as boas-novas à sua própria cidade.</p>",
    "associations": {
      "passage": [
        {
          "start_ref": "51001007",
          "start_ref_usfm": "COL 1:7",
          "end_ref": "51001007",
          "end_ref_usfm": "COL 1:7"
        }
      ],
      "resource": []
    }
  },
  {
    "content_id": 716027,
    "reference_id": 8991,
    "title": "Colossenses 1.9–10",
    "media_type": "Text",
    "index_reference": "51001009-51001010",
    "language": "por",
    "content": "<p>Paulo ora para que Deus conceda aos seus leitores uma compreensão mais profunda das boas-novas e sua plena expressão em suas vidas. O crescimento espiritual proporciona uma compreensão mais clara e profunda da verdade cristã e da conduta que agrada ao Senhor, através da qual um crente terá a resistência e paciência para se manter firme contra o mal (<a href=\"https://ref.ly/Col1:11\">1.11</a>).</p>",
    "associations": {
      "passage": [
        {
          "start_ref": "51001009",
          "start_ref_usfm": "COL 1:9",
          "end_ref": "51001010",
          "end_ref_usfm": "COL 1:10"
        }
      ],
      "resource": []
    }
  },
  {
    "content_id": 716006,
    "reference_id": 8970,
    "title": "Colossenses 1.12–13",
    "media_type": "Text",
    "index_reference": "51001012-51001013",
    "language": "por",
    "content": "<p>Sempre agradecendo ao Pai: A gratidão humilde a Deus pela salvação é um poderoso antídoto contra a atração do falso ensino (veja também <a href=\"https://ref.ly/Col2:7\">2.7</a>; <a href=\"https://ref.ly/Col3:17\">3.17</a>; <a href=\"https://ref.ly/Col4:2\">4.2</a>). • A herança é o que Deus prometeu ao seu povo (e.g., veja <a href=\"https://ref.ly/Deut3:28\">Dt 3.28</a>; <a href=\"https://ref.ly/Ps33:12\">Sl 33.12</a>; <a href=\"https://ref.ly/Ezek44:28\">Ez 44.28</a>). No Novo Testamento, <em>a herança</em> consiste na salvação e na libertação final (veja também <a href=\"https://ref.ly/Eph1:11\">Ef 1.11</a>; <a href=\"https://ref.ly/Titus3:7\">Tt 3.7</a>; <a href=\"https://ref.ly/Heb9:15\">Hb 9.15</a>).</p>",
    "associations": {
      "passage": [
        {
          "start_ref": "51001012",
          "start_ref_usfm": "COL 1:12",
          "end_ref": "51001013",
          "end_ref_usfm": "COL 1:13"
        }
      ],
      "resource": []
    }
  },
  {
    "content_id": 716008,
    "reference_id": 8972,
    "title": "Colossenses 1.15",
    "media_type": "Text",
    "index_reference": "51001015",
    "language": "por",
    "content": "<ul><li><p><em>a imagem</em>: Na tradução grega do Antigo Testamento, <em>eikōn</em> significa &quot;imagem&quot; ou &quot;representação&quot;. Descreve os humanos como feitos à imagem de Deus (<a href=\"https://ref.ly/Gen1:26-Gen1:27\">Gn 1.26–27</a>). Também se refere à figura da sabedoria nos escritos judaicos (veja Sabedoria de Salomão 7.25–26). Os escritores do Novo Testamento descrevem Cristo como &quot;a sabedoria de Deus&quot; para explicar sua importância (compare <a href=\"https://ref.ly/1Cor1:24\">1Co 1.24</a>, <a href=\"https://ref.ly/1Cor1:30\">30</a>).</p></li><li><p><em>o primogênito sobre toda a criação</em>: Esta frase foi importante nos debates cristãos primitivos sobre a natureza de Cristo. <em>Primogênito</em> não significa que Deus o criou. É um título do Antigo Testamento, indicando supremacia em posição e prioridade no tempo (veja, e.g., <a href=\"https://ref.ly/Ps89:27\">Sl 89.27</a>).</p></li></ul>",
    "associations": {
      "passage": [
        {
          "start_ref": "51001015",
          "start_ref_usfm": "COL 1:15",
          "end_ref": "51001015",
          "end_ref_usfm": "COL 1:15"
        }
      ],
      "resource": []
    }
  },
  {
    "content_id": 716007,
    "reference_id": 8971,
    "title": "Colossenses 1.15–20",
    "media_type": "Text",
    "index_reference": "51001015-51001020",
    "language": "por",
    "content": "<p>Paulo apresenta Jesus como o supremo criador (<a href=\"https://ref.ly/Col1:15-Col1:17\">1.15–17</a>) e redentor (<a href=\"https://ref.ly/Col1:18-Col1:20\">1.18–20</a>). A série de declarações curtas, as concepções exaltadas de Cristo e o paralelismo na linguagem e no pensamento sugerem fortemente que esses versículos citam um hino cristão primitivo sobre Jesus que Paulo aplicou à situação dos cristãos colossenses.</p>",
    "associations": {
      "passage": [
        {
          "start_ref": "51001015",
          "start_ref_usfm": "COL 1:15",
          "end_ref": "51001020",
          "end_ref_usfm": "COL 1:20"
        }
      ],
      "resource": []
    }
  },
  {
    "content_id": 716009,
    "reference_id": 8973,
    "title": "Colossenses 1.16",
    "media_type": "Text",
    "index_reference": "51001016",
    "language": "por",
    "content": "<p>Tronos, reinos, governantes e autoridades no mundo invisível referem-se a várias potências espirituais. Esta linha enfatiza a supremacia de Cristo sobre esses seres que estavam recebendo tanta atenção dos falsos mestres (veja <a href=\"https://ref.ly/Col2:18\">2.18</a>). • Tudo foi criado por meio dele e para ele: Cristo é tanto aquele por meio de quem todas as coisas foram criadas quanto o objetivo de toda a criação.</p>",
    "associations": {
      "passage": [
        {
          "start_ref": "51001016",
          "start_ref_usfm": "COL 1:16",
          "end_ref": "51001016",
          "end_ref_usfm": "COL 1:16"
        }
      ],
      "resource": []
    }
  },
  {
    "content_id": 716010,
    "reference_id": 8974,
    "title": "Colossenses 1.18",
    "media_type": "Text",
    "index_reference": "51001018",
    "language": "por",
    "content": "<p>cabeça da igreja: A palavra grega kephalē (cabeça) geralmente significa <em>autoridade sobre</em> ou <em>chefe</em> quando Paulo a utiliza como metáfora (veja também <a href=\"https://ref.ly/Col2:10\">2.10</a>,<a href=\"https://ref.ly/Col2:19\">19</a>; <a href=\"https://ref.ly/1Cor11:3-1Cor11:10\">1Co 11.3–10</a>; <a href=\"https://ref.ly/Eph4:15\">Ef 4.15</a>; <a href=\"https://ref.ly/Eph5:23\">5.23</a>). • que é o seu corpo: A metáfora da igreja como o corpo de Cristo expressa a unidade essencial de Cristo e a igreja (veja também <a href=\"https://ref.ly/Col1:24\">Cl 1.24</a>; <a href=\"https://ref.ly/Col2:19\">2.19</a>; <a href=\"https://ref.ly/Col3:15\">3.15</a>; <a href=\"https://ref.ly/Eph1:23\">Ef 1.23</a>; <a href=\"https://ref.ly/Eph2:16\">2.16</a>; <a href=\"https://ref.ly/Eph4:4\">4.4</a>,<a href=\"https://ref.ly/Eph4:12\">12</a>; <a href=\"https://ref.ly/Eph5:23\">5.23</a>,<a href=\"https://ref.ly/Eph5:30\">30</a>). • supremo sobre todos os que ressuscitam dos mortos (ou <em>o primogênito dos mortos</em>): Veja <span data-bnType=\"resourceReference\" data-resourceId=\"8972\" data-resourceType=\"TyndaleStudyNotes\">nota de estudo em Cl 1.15</span>.</p>",
    "associations": {
      "passage": [
        {
          "start_ref": "51001018",
          "start_ref_usfm": "COL 1:18",
          "end_ref": "51001018",
          "end_ref_usfm": "COL 1:18"
        }
      ],
      "resource": [
        {
          "reference_id": 8972,
          "content_id": 716008,
          "resource_code": "TyndaleStudyNotes",
          "label": "Colossenses 1.15",
          "language": "por"
        }
      ]
    }
  },
  {
    "content_id": 716011,
    "reference_id": 8975,
    "title": "Colossenses 1.19",
    "media_type": "Text",
    "index_reference": "51001019",
    "language": "por",
    "content": "<p>Deus em toda a sua plenitude enfatiza que Ele escolheu se revelar completamente em Jesus Cristo. Ver e entender Jesus, portanto, significa ver e entender Deus (veja <a href=\"https://ref.ly/John14:6-John14:11\">Jo 14.6–11</a>). Os falsos mestres pareciam estar dizendo que os cristãos precisavam olhar para outros seres espirituais para saber mais sobre Deus (veja <a href=\"https://ref.ly/Col1:16\">Cl 1.16</a>, <a href=\"https://ref.ly/Col1:20\">20</a>). Mas Cristo é suficiente para todo o nosso conhecimento de Deus (cp. <a href=\"https://ref.ly/Col2:8-Col2:9\">2.8–9</a>).</p>",
    "associations": {
      "passage": [
        {
          "start_ref": "51001019",
          "start_ref_usfm": "COL 1:19",
          "end_ref": "51001019",
          "end_ref_usfm": "COL 1:19"
        }
      ],
      "resource": []
    }
  },
  {
    "content_id": 716013,
    "reference_id": 8977,
    "title": "Colossenses 1.20",
    "media_type": "Text",
    "index_reference": "51001020",
    "language": "por",
    "content": "<p>Através de Cristo, Deus reconciliou tudo consigo, restabelecendo seu domínio sobre toda a criação, incluindo tanto os reinos espirituais quanto os terrenos.</p>",
    "associations": {
      "passage": [
        {
          "start_ref": "51001020",
          "start_ref_usfm": "COL 1:20",
          "end_ref": "51001020",
          "end_ref_usfm": "COL 1:20"
        }
      ],
      "resource": []
    }
  },
  {
    "content_id": 716015,
    "reference_id": 8979,
    "title": "Colossenses 1.21",
    "media_type": "Text",
    "index_reference": "51001021",
    "language": "por",
    "content": "<p>A frase &quot;uma vez longe de Deus&quot; provavelmente se refere à condição deles como gentios (veja <a href=\"https://ref.ly/Eph2:12\">Ef 2.12</a>).</p>",
    "associations": {
      "passage": [
        {
          "start_ref": "51001021",
          "start_ref_usfm": "COL 1:21",
          "end_ref": "51001021",
          "end_ref_usfm": "COL 1:21"
        }
      ],
      "resource": []
    }
  },
  {
    "content_id": 716014,
    "reference_id": 8978,
    "title": "Colossenses 1.21–23",
    "media_type": "Text",
    "index_reference": "51001021-51001023",
    "language": "por",
    "content": "<p>Paulo aplica a verdade de <a href=\"https://ref.ly/Col1:15-Col1:20\">1.15–20</a> aos cristãos colossenses. Como pessoas que foram reconciliadas com Deus, eles desfrutam de um novo status espiritual e precisam permanecer firmes na verdade que lhes foi ensinada.</p>",
    "associations": {
      "passage": [
        {
          "start_ref": "51001021",
          "start_ref_usfm": "COL 1:21",
          "end_ref": "51001023",
          "end_ref_usfm": "COL 1:23"
        }
      ],
      "resource": []
    }
  },
  {
    "content_id": 716016,
    "reference_id": 8980,
    "title": "Colossenses 1.22",
    "media_type": "Text",
    "index_reference": "51001022",
    "language": "por",
    "content": "<p>Os colossenses, assim como todos os crentes, eram santos e irrepreensíveis aos olhos de Deus, não por causa de sua própria perfeição, mas porque foram reconciliados com Deus através da morte de Cristo.</p>",
    "associations": {
      "passage": [
        {
          "start_ref": "51001022",
          "start_ref_usfm": "COL 1:22",
          "end_ref": "51001022",
          "end_ref_usfm": "COL 1:22"
        }
      ],
      "resource": []
    }
  },
  {
    "content_id": 716017,
    "reference_id": 8981,
    "title": "Colossenses 1.23",
    "media_type": "Text",
    "index_reference": "51001023",
    "language": "por",
    "content": "<p>pregado em todo o mundo (literalmente <em>pregado a toda criatura debaixo do céu</em>): O ponto da hipérbole de Paulo (exagero para ênfase) é que centros para a pregação das boas-novas haviam sido estabelecidos em cidades chave por todo o mundo romano (veja também <a href=\"https://ref.ly/Col1:6\">1.6</a>).</p>",
    "associations": {
      "passage": [
        {
          "start_ref": "51001023",
          "start_ref_usfm": "COL 1:23",
          "end_ref": "51001023",
          "end_ref_usfm": "COL 1:23"
        }
      ],
      "resource": []
    }
  },
  {
    "content_id": 716019,
    "reference_id": 8983,
    "title": "Colossenses 1.24",
    "media_type": "Text",
    "index_reference": "51001024",
    "language": "por",
    "content": "<p>Estou participando dos sofrimentos de Cristo (literalmente <em>estou completando o que falta nos sofrimentos de Cristo</em>): Embora o sofrimento redentor de Cristo seja único e completamente concluído, Cristo ainda sofre através de seu povo em um mundo hostil à mensagem de redenção. Cristo e sua igreja continuarão a sofrer até que os propósitos de Deus neste mundo sejam completos (veja também <a href=\"https://ref.ly/Mark13:19-Mark13:23\">Mc 13.19–23</a>; <a href=\"https://ref.ly/Rom8:17-Rom8:18\">Rm 8.17–18</a>; <a href=\"https://ref.ly/1Thess3:3\">1Ts 3.3</a>).</p>",
    "associations": {
      "passage": [
        {
          "start_ref": "51001024",
          "start_ref_usfm": "COL 1:24",
          "end_ref": "51001024",
          "end_ref_usfm": "COL 1:24"
        }
      ],
      "resource": []
    }
  },
  {
    "content_id": 716018,
    "reference_id": 8982,
    "title": "Colossenses 1.24–2:5",
    "media_type": "Text",
    "index_reference": "51001024-51002005",
    "language": "por",
    "content": "<p>Paulo reflete sobre seu papel na ampla pregação das boas-novas (<a href=\"https://ref.ly/Col1:23\">1.23</a>).</p>",
    "associations": {
      "passage": [
        {
          "start_ref": "51001024",
          "start_ref_usfm": "COL 1:24",
          "end_ref": "51002005",
          "end_ref_usfm": "COL 2:5"
        }
      ],
      "resource": []
    }
  },
  {
    "content_id": 716020,
    "reference_id": 8984,
    "title": "Colossenses 1.26",
    "media_type": "Text",
    "index_reference": "51001026",
    "language": "por",
    "content": "<p>O conceito de um segredo, oculto em um momento e depois revelado, é baseado em ideias apocalípticas judaicas. Os pensadores judeus concebiam todo o plano de Deus como já existente no céu, oculto até que Deus decidisse puxar a cortina e revelá-lo. As boas-novas, especialmente para os gentios, foram mantidas em segredo até serem reveladas em Cristo.</p>",
    "associations": {
      "passage": [
        {
          "start_ref": "51001026",
          "start_ref_usfm": "COL 1:26",
          "end_ref": "51001026",
          "end_ref_usfm": "COL 1:26"
        }
      ],
      "resource": []
    }
  },
  {
    "content_id": 716028,
    "reference_id": 8992,
    "title": "Colossenses 2.1–5",
    "media_type": "Text",
    "index_reference": "51002001-51002005",
    "language": "por",
    "content": "<p>Paulo expressa sua preocupação em fortalecer seu relacionamento com os colossenses, a quem ele não conhecia, e em combater as ideias heréticas que ameaçavam sua comunidade cristã. • Laodiceia estava localizada a 10 quilômetros a noroeste de Colossos.</p>",
    "associations": {
      "passage": [
        {
          "start_ref": "51002001",
          "start_ref_usfm": "COL 2:1",
          "end_ref": "51002005",
          "end_ref_usfm": "COL 2:5"
        }
      ],
      "resource": []
    }
  },
  {
    "content_id": 716039,
    "reference_id": 9003,
    "title": "Colossenses 2.2",
    "media_type": "Text",
    "index_reference": "51002002",
    "language": "por",
    "content": "<p>O plano misterioso de Deus: Veja <a href=\"https://ref.ly/Col1:26\">1.26</a>; o próprio Cristo personifica este plano.</p>",
    "associations": {
      "passage": [
        {
          "start_ref": "51002002",
          "start_ref_usfm": "COL 2:2",
          "end_ref": "51002002",
          "end_ref_usfm": "COL 2:2"
        }
      ],
      "resource": []
    }
  },
  {
    "content_id": 716040,
    "reference_id": 9004,
    "title": "Colossenses 2.3",
    "media_type": "Text",
    "index_reference": "51002003",
    "language": "por",
    "content": "<p>Paulo desenvolve em <a href=\"https://ref.ly/Col1:15-Col1:20\">1.15–20</a>: Somente Cristo é suficiente para o nosso entendimento espiritual.</p>",
    "associations": {
      "passage": [
        {
          "start_ref": "51002003",
          "start_ref_usfm": "COL 2:3",
          "end_ref": "51002003",
          "end_ref_usfm": "COL 2:3"
        }
      ],
      "resource": []
    }
  },
  {
    "content_id": 716041,
    "reference_id": 9005,
    "title": "Colossenses 2.6–15",
    "media_type": "Text",
    "index_reference": "51002006-51002015",
    "language": "por",
    "content": "<p>Diante dos argumentos sedutores dos falsos mestres, Paulo exorta os colossenses a permanecerem firmes em sua fé em Cristo, pois em Cristo habita toda a plenitude de Deus<em>,</em> e sua experiência espiritual é plena nele.</p>",
    "associations": {
      "passage": [
        {
          "start_ref": "51002006",
          "start_ref_usfm": "COL 2:6",
          "end_ref": "51002015",
          "end_ref_usfm": "COL 2:15"
        }
      ],
      "resource": []
    }
  },
  {
    "content_id": 716042,
    "reference_id": 9006,
    "title": "Colossenses 2.8",
    "media_type": "Text",
    "index_reference": "51002008",
    "language": "por",
    "content": "<p>A palavra grega philosophia refere-se a tudo, desde a metafísica de Platão até o ensino religioso de cultos. Paulo não condena a filosofia em si, mas apenas a especulação filosófica vazia que se opõe às boas-novas. • os poderes espirituais deste mundo: ou <em>os princípios espirituais do mundo;</em> também em <a href=\"https://ref.ly/Col2:20\">2.20</a>): Esta frase pode referir-se ao ensino elementar que é característico deste mundo (veja <a href=\"https://ref.ly/Heb5:12\">Hb 5.12</a>), ou a seres espirituais que se pensava ter uma influência decisiva no curso dos eventos (veja também <a href=\"https://ref.ly/Col2:15\">Cl 2.15</a>, <a href=\"https://ref.ly/Col2:20\">20</a>; <a href=\"https://ref.ly/Gal4:3\">Gl 4.3</a>).</p>",
    "associations": {
      "passage": [
        {
          "start_ref": "51002008",
          "start_ref_usfm": "COL 2:8",
          "end_ref": "51002008",
          "end_ref_usfm": "COL 2:8"
        }
      ],
      "resource": []
    }
  },
  {
    "content_id": 716029,
    "reference_id": 8993,
    "title": "Colossenses 2.11",
    "media_type": "Text",
    "index_reference": "51002011",
    "language": "por",
    "content": "<p>Cristo realizou uma circuncisão espiritual: A conversão espiritual a Cristo é a contraparte cristã da circuncisão física. • o corte da sua natureza pecaminosa (literalmente <em>o corte do corpo da carne</em>): Assim como os meninos judeus têm a carne do prepúcio cortada para marcar sua iniciação no povo de Deus, os crentes têm a <em>carne</em> metafórica (traduzida como <em>natureza pecaminosa</em>) cortada quando se voltam para Cristo.</p>",
    "associations": {
      "passage": [
        {
          "start_ref": "51002011",
          "start_ref_usfm": "COL 2:11",
          "end_ref": "51002011",
          "end_ref_usfm": "COL 2:11"
        }
      ],
      "resource": []
    }
  },
  {
    "content_id": 716030,
    "reference_id": 8994,
    "title": "Colossenses 2.12",
    "media_type": "Text",
    "index_reference": "51002012",
    "language": "por",
    "content": "<p>Vocês foram sepultados com Cristo quando foram batizados: Como em uma passagem aproximadamente paralela (<a href=\"https://ref.ly/Rom6:3-Rom6:6\">Rm 6.3–6</a>), Paulo estabelece uma forte identidade entre os crentes e Cristo. Aos olhos de Deus, realmente estávamos <em>com Cristo</em> quando Ele foi sepultado e ressuscitado, então experimentamos os benefícios do que Cristo fez por nós. Paulo pode vincular essa identificação com Cristo ao batismo porque o batismo em água estava tão intimamente relacionado à conversão na igreja primitiva.</p>",
    "associations": {
      "passage": [
        {
          "start_ref": "51002012",
          "start_ref_usfm": "COL 2:12",
          "end_ref": "51002012",
          "end_ref_usfm": "COL 2:12"
        }
      ],
      "resource": []
    }
  },
  {
    "content_id": 716031,
    "reference_id": 8995,
    "title": "Colossenses 2.14",
    "media_type": "Text",
    "index_reference": "51002014",
    "language": "por",
    "content": "<p>O registro das acusações contra nós: A frase grega sugere uma nota promissória que todos nós assinamos. Como não somos capazes de pagar o que devemos, ela permanece <em>contra nós.</em> A lei de Deus exigia uma obediência que as pessoas não conseguem oferecer, mas Deus perdoou nossa dívida através da obra de Cristo (<a href=\"https://ref.ly/Col2:13\">2.13</a>).</p>",
    "associations": {
      "passage": [
        {
          "start_ref": "51002014",
          "start_ref_usfm": "COL 2:14",
          "end_ref": "51002014",
          "end_ref_usfm": "COL 2:14"
        }
      ],
      "resource": []
    }
  },
  {
    "content_id": 716032,
    "reference_id": 8996,
    "title": "Colossenses 2.15",
    "media_type": "Text",
    "index_reference": "51002015",
    "language": "por",
    "content": "<p>Ele os envergonhou publicamente com sua vitória (literalmente <em>ele os conduziu em procissão triunfal</em>): O exército romano celebrava uma grande vitória com uma procissão triunfal. O general romano vitorioso conduzia os cativos humilhados de sua campanha para a cidade conquistada. A imagem captura vividamente a gloriosa vitória que Deus, através da cruz de Cristo, conquistou sobre todos os poderes espirituais hostis (veja também <a href=\"https://ref.ly/Eph4:7-Eph4:11\">Ef 4.7–11</a>).</p>",
    "associations": {
      "passage": [
        {
          "start_ref": "51002015",
          "start_ref_usfm": "COL 2:15",
          "end_ref": "51002015",
          "end_ref_usfm": "COL 2:15"
        }
      ],
      "resource": []
    }
  },
  {
    "content_id": 716034,
    "reference_id": 8998,
    "title": "Colossenses 2.16",
    "media_type": "Text",
    "index_reference": "51002016",
    "language": "por",
    "content": "<p>O que você come ou bebe: Ensinamentos religiosos que proibiam certos tipos de alimentos e bebidas eram comuns no mundo antigo. O Antigo Testamento não proíbe o consumo de álcool, mas muitos judeus piedosos que viviam em culturas pagãs se abstinham (cp. <a href=\"https://ref.ly/Dan1:8-Dan1:16\">Dn 1.8–16</a>). • Muitos grupos religiosos antigos, incluindo os judeus, celebravam a lua nova com várias cerimônias (veja <a href=\"https://ref.ly/Num10:10\">Nm 10.10</a>; <a href=\"https://ref.ly/Ps81:3\">Sl 81.3</a>; <a href=\"https://ref.ly/Isa1:13\">Is 1.13</a>). • Os sábados judaicos eram estabelecidos na lei de Moisés e celebrados pelos judeus como parte essencial de sua religião. Os cristãos podiam continuar a observar o sábado se quisessem, mas Paulo afirma que os cristãos têm liberdade nessa questão (veja <a href=\"https://ref.ly/Rom14:5\">Rm 14.5</a>) e que é errado alguém insistir na observância do sábado como uma expressão necessária de piedade cristã.</p>",
    "associations": {
      "passage": [
        {
          "start_ref": "51002016",
          "start_ref_usfm": "COL 2:16",
          "end_ref": "51002016",
          "end_ref_usfm": "COL 2:16"
        }
      ],
      "resource": []
    }
  },
  {
    "content_id": 716033,
    "reference_id": 8997,
    "title": "Colossenses 2.16–23",
    "media_type": "Text",
    "index_reference": "51002016-51002023",
    "language": "por",
    "content": "<p>Paulo repudia os falsos mestres e suas exigências, explicando por que seus apelos vêm de ensinamentos humanos (veja <a href=\"https://ref.ly/Col2:8\">2.8</a>). Eles defendiam várias regras de conduta que não tinham base em Cristo.</p>",
    "associations": {
      "passage": [
        {
          "start_ref": "51002016",
          "start_ref_usfm": "COL 2:16",
          "end_ref": "51002023",
          "end_ref_usfm": "COL 2:23"
        }
      ],
      "resource": []
    }
  },
  {
    "content_id": 716035,
    "reference_id": 8999,
    "title": "Colossenses 2.17",
    "media_type": "Text",
    "index_reference": "51002017",
    "language": "por",
    "content": "<p>A realidade de Cristo foi antecipada pelos rituais do Antigo Testamento, que Paulo chama de sombras (veja também <a href=\"https://ref.ly/Heb10:1\">Hb 10.1</a>).</p>",
    "associations": {
      "passage": [
        {
          "start_ref": "51002017",
          "start_ref_usfm": "COL 2:17",
          "end_ref": "51002017",
          "end_ref_usfm": "COL 2:17"
        }
      ],
      "resource": []
    }
  },
  {
    "content_id": 716036,
    "reference_id": 9000,
    "title": "Colossenses 2.18",
    "media_type": "Text",
    "index_reference": "51002018",
    "language": "por",
    "content": "<p>adoração de anjos: As pessoas no primeiro século estavam fascinadas por seres espirituais. Alguns judeus acreditavam que os anjos estavam presentes durante seus momentos de adoração, e alguns talvez até os adorassem. • Os falsos mestres aparentemente afirmavam ter tido visões que estabeleciam certos rituais como requisitos para a comunidade.</p>",
    "associations": {
      "passage": [
        {
          "start_ref": "51002018",
          "start_ref_usfm": "COL 2:18",
          "end_ref": "51002018",
          "end_ref_usfm": "COL 2:18"
        }
      ],
      "resource": []
    }
  },
  {
    "content_id": 716037,
    "reference_id": 9001,
    "title": "Colossenses 2.20",
    "media_type": "Text",
    "index_reference": "51002020",
    "language": "por",
    "content": "<p>Você morreu com Cristo: a morte de Cristo na cruz marcou sua vitória sobre os poderes espirituais (<a href=\"https://ref.ly/Col2:15\">2.15</a>), então nós que participamos de sua morte também fomos libertados dos poderes espirituais malignos deste mundo (veja <a href=\"https://ref.ly/Col2:8\">2.8</a>).</p>",
    "associations": {
      "passage": [
        {
          "start_ref": "51002020",
          "start_ref_usfm": "COL 2:20",
          "end_ref": "51002020",
          "end_ref_usfm": "COL 2:20"
        }
      ],
      "resource": []
    }
  },
  {
    "content_id": 716038,
    "reference_id": 9002,
    "title": "Colossenses 2.23",
    "media_type": "Text",
    "index_reference": "51002023",
    "language": "por",
    "content": "<p>eles não oferecem ajuda: Essas regras não apenas estão enraizadas no mundo em vez de em Cristo (<a href=\"https://ref.ly/Col2:19\">2.19</a>), mas também são ineficazes em controlar os desejos malignos de uma pessoa.</p>",
    "associations": {
      "passage": [
        {
          "start_ref": "51002023",
          "start_ref_usfm": "COL 2:23",
          "end_ref": "51002023",
          "end_ref_usfm": "COL 2:23"
        }
      ],
      "resource": []
    }
  },
  {
    "content_id": 716052,
    "reference_id": 9016,
    "title": "Colossenses 3.1",
    "media_type": "Text",
    "index_reference": "51003001",
    "language": "por",
    "content": "<p>Concentre-se nas realidades do céu: os cristãos vivem na terra, mas, por terem sido ressuscitados com Cristo, seu verdadeiro ser está voltado para o reino espiritual sobre o qual Cristo governa. Em contraste, as regras e regulamentos dos falsos mestres focavam no reino terreno (<a href=\"https://ref.ly/Col2:22\">2.22</a>).</p>",
    "associations": {
      "passage": [
        {
          "start_ref": "51003001",
          "start_ref_usfm": "COL 3:1",
          "end_ref": "51003001",
          "end_ref_usfm": "COL 3:1"
        }
      ],
      "resource": []
    }
  },
  {
    "content_id": 716043,
    "reference_id": 9007,
    "title": "Colossenses 3.1–11",
    "media_type": "Text",
    "index_reference": "51003001-51003011",
    "language": "por",
    "content": "<p>Paulo convoca os colossenses a adotarem uma nova maneira de pensar que resulta em um novo estilo de vida.</p>",
    "associations": {
      "passage": [
        {
          "start_ref": "51003001",
          "start_ref_usfm": "COL 3:1",
          "end_ref": "51003011",
          "end_ref_usfm": "COL 3:11"
        }
      ],
      "resource": []
    }
  },
  {
    "content_id": 716054,
    "reference_id": 9018,
    "title": "Colossenses 3.3–4",
    "media_type": "Text",
    "index_reference": "51003003-51003004",
    "language": "por",
    "content": "<p>você morreu para esta vida: Veja <a href=\"https://ref.ly/Col2:20\">2.20</a>. • O que agora está oculto um dia será revelado (cp. <a href=\"https://ref.ly/Col1:26\">1.26</a>). Não podemos ver agora que Cristo está entronizado à direita de Deus e que fomos ressuscitados para uma nova vida com Cristo. Mas, pela fé nas boas-novas, sabemos que essas coisas são verdadeiras. Quando Cristo retornar em glória, sua supremacia será evidente para todos, e nosso relacionamento com ele será uma experiência direta.</p>",
    "associations": {
      "passage": [
        {
          "start_ref": "51003003",
          "start_ref_usfm": "COL 3:3",
          "end_ref": "51003004",
          "end_ref_usfm": "COL 3:4"
        }
      ],
      "resource": []
    }
  },
  {
    "content_id": 716055,
    "reference_id": 9019,
    "title": "Colossenses 3.5",
    "media_type": "Text",
    "index_reference": "51003005",
    "language": "por",
    "content": "<p>Portanto, mortifique: Nossa morte para esta vida (<a href=\"https://ref.ly/Col3:3\">3.3</a>) deve se tornar real na maneira como vivemos dia a dia. • uma pessoa gananciosa é um idólatra: Pessoas gananciosas buscam os objetos de sua ganância — dinheiro, sexo, poder, posses — no lugar de Deus, com a esperança de encontrar satisfação nessas coisas.</p>",
    "associations": {
      "passage": [
        {
          "start_ref": "51003005",
          "start_ref_usfm": "COL 3:5",
          "end_ref": "51003005",
          "end_ref_usfm": "COL 3:5"
        }
      ],
      "resource": []
    }
  },
  {
    "content_id": 716056,
    "reference_id": 9020,
    "title": "Colossenses 3.6",
    "media_type": "Text",
    "index_reference": "51003006",
    "language": "por",
    "content": "<p>vindo: Alguns manuscritos dizem <em>vindo sobre todos os que o desobedecem.</em> No texto grego, essas palavras ocorrem literalmente em <a href=\"https://ref.ly/Eph5:6\">Ef 5.6</a>, então é possível que um escriba antigo as tenha adicionado aqui, intencionalmente ou acidentalmente.</p>",
    "associations": {
      "passage": [
        {
          "start_ref": "51003006",
          "start_ref_usfm": "COL 3:6",
          "end_ref": "51003006",
          "end_ref_usfm": "COL 3:6"
        }
      ],
      "resource": []
    }
  },
  {
    "content_id": 716057,
    "reference_id": 9021,
    "title": "Colossenses 3.8",
    "media_type": "Text",
    "index_reference": "51003008",
    "language": "por",
    "content": "<p>livrar-se de (literalmente <em>tirar</em>): Tirar a roupa é uma metáfora para nos livrarmos de práticas que interferem em nosso caminhar com o Senhor (veja <a href=\"https://ref.ly/Rom13:12\">Rm 13.12</a>; <a href=\"https://ref.ly/Eph4:22\">Ef 4.22</a>, <a href=\"https://ref.ly/Eph4:25\">25</a>; <a href=\"https://ref.ly/Heb12:1\">Hb 12.1</a>; <a href=\"https://ref.ly/Jas1:21\">Tg 1.21</a>; <a href=\"https://ref.ly/1Pet2:1\">1Pe 2.1</a>).</p>",
    "associations": {
      "passage": [
        {
          "start_ref": "51003008",
          "start_ref_usfm": "COL 3:8",
          "end_ref": "51003008",
          "end_ref_usfm": "COL 3:8"
        }
      ],
      "resource": []
    }
  },
  {
    "content_id": 716058,
    "reference_id": 9022,
    "title": "Colossenses 3.9–10",
    "media_type": "Text",
    "index_reference": "51003009-51003010",
    "language": "por",
    "content": "<p><em>o velho eu… o novo eu</em>: Paulo contrasta identidades antigas e novas (veja também <a href=\"https://ref.ly/Rom5:12-Rom5:21\">Rm 5.12–21</a>; <a href=\"https://ref.ly/Rom6:6\">6.6</a>; <a href=\"https://ref.ly/Eph4:22-Eph4:24\">Ef 4.22–24</a>). Os crentes deixam de viver como antes e começam a viver uma nova vida em Cristo, permitindo que Ele seja o Senhor e guie a maneira como vivem.</p>",
    "associations": {
      "passage": [
        {
          "start_ref": "51003009",
          "start_ref_usfm": "COL 3:9",
          "end_ref": "51003010",
          "end_ref_usfm": "COL 3:10"
        }
      ],
      "resource": []
    }
  },
  {
    "content_id": 716044,
    "reference_id": 9008,
    "title": "Colossenses 3.11",
    "media_type": "Text",
    "index_reference": "51003011",
    "language": "por",
    "content": "<p>bárbaro, incivilizado: Literalmente <em>Bárbaro, Cita.</em> Os gregos zombavam de pessoas de outras culturas por sua incapacidade de falar bem o grego, alegando que só conseguiam dizer “bar bar” (daí a palavra <em>bárbaro</em>). Os citas eram tribos que se estabeleceram na costa norte do Mar Negro e eram amplamente vistas como ferozes e rudes (veja Josefo, <em>Contra Apião</em> 2.38). Todas essas distinções não importam em nosso relacionamento com Deus através de Cristo.</p>",
    "associations": {
      "passage": [
        {
          "start_ref": "51003011",
          "start_ref_usfm": "COL 3:11",
          "end_ref": "51003011",
          "end_ref_usfm": "COL 3:11"
        }
      ],
      "resource": []
    }
  },
  {
    "content_id": 716045,
    "reference_id": 9009,
    "title": "Colossenses 3.12–17",
    "media_type": "Text",
    "index_reference": "51003012-51003017",
    "language": "por",
    "content": "<p>Paulo descreve a natureza da nova vida das pessoas que foram ressuscitadas com Cristo (<a href=\"https://ref.ly/Col3:1\">3.1</a>). Suas virtudes e atividades contribuem para a paz e a força da comunidade cristã.</p>",
    "associations": {
      "passage": [
        {
          "start_ref": "51003012",
          "start_ref_usfm": "COL 3:12",
          "end_ref": "51003017",
          "end_ref_usfm": "COL 3:17"
        }
      ],
      "resource": []
    }
  },
  {
    "content_id": 716046,
    "reference_id": 9010,
    "title": "Colossenses 3.15",
    "media_type": "Text",
    "index_reference": "51003015",
    "language": "por",
    "content": "<p>Assim como Cristo é um, só pode haver um corpo de Cristo (veja <a href=\"https://ref.ly/Col1:18\">1.18</a>; <a href=\"https://ref.ly/Eph4:4-Eph4:6\">Ef 4.4–6</a>). A lealdade a Jesus como Senhor deve transcender as diferenças e resultará em paz (relacionamentos harmoniosos).</p>",
    "associations": {
      "passage": [
        {
          "start_ref": "51003015",
          "start_ref_usfm": "COL 3:15",
          "end_ref": "51003015",
          "end_ref_usfm": "COL 3:15"
        }
      ],
      "resource": []
    }
  },
  {
    "content_id": 716047,
    "reference_id": 9011,
    "title": "Colossenses 3.16",
    "media_type": "Text",
    "index_reference": "51003016",
    "language": "por",
    "content": "<p>Salmos, hinos e cânticos espirituais são canções de louvor e adoração (veja <a href=\"https://ref.ly/1Cor14:26\">1Co 14.26</a>; <a href=\"https://ref.ly/Eph5:19\">Ef 5.19</a>). O protótipo é o livro de Salmos.</p>",
    "associations": {
      "passage": [
        {
          "start_ref": "51003016",
          "start_ref_usfm": "COL 3:16",
          "end_ref": "51003016",
          "end_ref_usfm": "COL 3:16"
        }
      ],
      "resource": []
    }
  },
  {
    "content_id": 716048,
    "reference_id": 9012,
    "title": "Colossenses 3.17",
    "media_type": "Text",
    "index_reference": "51003017",
    "language": "por",
    "content": "<p>Como representante do Senhor Jesus (literalmente <em>em nome do Senhor Jesus</em>): Na Bíblia, o nome de uma pessoa representa essa pessoa. Fazer algo <em>em nome</em> <em>do Senhor Jesus</em> significa agir de uma maneira que esteja em harmonia com sua identidade e sob sua autoridade.</p>",
    "associations": {
      "passage": [
        {
          "start_ref": "51003017",
          "start_ref_usfm": "COL 3:17",
          "end_ref": "51003017",
          "end_ref_usfm": "COL 3:17"
        }
      ],
      "resource": []
    }
  },
  {
    "content_id": 716050,
    "reference_id": 9014,
    "title": "Colossenses 3.18",
    "media_type": "Text",
    "index_reference": "51003018",
    "language": "por",
    "content": "<p>Submeter-se é reconhecer o próprio lugar sob outra pessoa em uma ordem social. Tal submissão sempre implica que Deus está no topo e que sua vontade é suprema (cp. <a href=\"https://ref.ly/Acts4:19-Acts4:20\">At 4.19–20</a>; <a href=\"https://ref.ly/Acts5:29\">5.29</a>).</p>",
    "associations": {
      "passage": [
        {
          "start_ref": "51003018",
          "start_ref_usfm": "COL 3:18",
          "end_ref": "51003018",
          "end_ref_usfm": "COL 3:18"
        }
      ],
      "resource": []
    }
  },
  {
    "content_id": 716049,
    "reference_id": 9013,
    "title": "Colossenses 3.18–4.1",
    "media_type": "Text",
    "index_reference": "51003018-51004001",
    "language": "por",
    "content": "<p>Esta série de exortações é chamada de <em>código doméstico.</em> Paulo dá instruções para esposas (<a href=\"https://ref.ly/Col3:18\">3.18</a>), maridos (<a href=\"https://ref.ly/Col3:19\">3.19</a>), filhos (<a href=\"https://ref.ly/Col3:20\">3.20</a>), pais (<a href=\"https://ref.ly/Col3:21\">3.21</a>), escravos (<a href=\"https://ref.ly/Col3:22-Col3:25\">3.22–25</a>) e senhores (<a href=\"https://ref.ly/Col4:1\">4.1</a>). Tais códigos aparecem em escritores greco-romanos e em outras partes do Novo Testamento (veja <a href=\"https://ref.ly/Eph5:22-Eph6:9\">Ef 5.22–6.9</a>; <a href=\"https://ref.ly/1Pet2:18-1Pet3:7\">1Pe 2.18–3.7</a>).</p>",
    "associations": {
      "passage": [
        {
          "start_ref": "51003018",
          "start_ref_usfm": "COL 3:18",
          "end_ref": "51004001",
          "end_ref_usfm": "COL 4:1"
        }
      ],
      "resource": []
    }
  },
  {
    "content_id": 716051,
    "reference_id": 9015,
    "title": "Colossenses 3.19",
    "media_type": "Text",
    "index_reference": "51003019",
    "language": "por",
    "content": "<p>A exortação às esposas para que se submetam aos seus maridos é imediatamente seguida por uma ordem aos maridos para que amem suas esposas (veja também <a href=\"https://ref.ly/Eph5:25-Eph5:30\">Ef 5.25–30</a>; <a href=\"https://ref.ly/1Pet3:7\">1Pe 3.7</a>).</p>",
    "associations": {
      "passage": [
        {
          "start_ref": "51003019",
          "start_ref_usfm": "COL 3:19",
          "end_ref": "51003019",
          "end_ref_usfm": "COL 3:19"
        }
      ],
      "resource": []
    }
  },
  {
    "content_id": 716053,
    "reference_id": 9017,
    "title": "Colossenses 3.22–24",
    "media_type": "Text",
    "index_reference": "51003022-51003024",
    "language": "por",
    "content": "<p>Os escravos têm mestres terrenos a quem devem obedecer. A escravidão era central para a vida e economia do mundo antigo, e o Novo Testamento nunca ataca a prática como tal. No entanto, a fé cristã estabelece relacionamentos que mudam a natureza da estrutura social (veja <a href=\"https://ref.ly/Phlm1:15-Phlm1:16\">Fm 1.15–16</a>). • e que o Mestre que você está servindo é Cristo: Todos os cristãos, tanto escravos quanto livres, servem a um Mestre superior, cuja vontade é primordial.</p>",
    "associations": {
      "passage": [
        {
          "start_ref": "51003022",
          "start_ref_usfm": "COL 3:22",
          "end_ref": "51003024",
          "end_ref_usfm": "COL 3:24"
        }
      ],
      "resource": []
    }
  },
  {
    "content_id": 716068,
    "reference_id": 9032,
    "title": "Colossenses 4.1",
    "media_type": "Text",
    "index_reference": "51004001",
    "language": "por",
    "content": "<p>Mestres: Os proprietários de escravos cristãos precisavam reconhecer que eles também eram servos obrigados a obedecer a Jesus Cristo, seu Mestre no céu, que trata todas as pessoas com dignidade e graça.</p>",
    "associations": {
      "passage": [
        {
          "start_ref": "51004001",
          "start_ref_usfm": "COL 4:1",
          "end_ref": "51004001",
          "end_ref_usfm": "COL 4:1"
        }
      ],
      "resource": []
    }
  },
  {
    "content_id": 716070,
    "reference_id": 9034,
    "title": "Colossenses 4.2",
    "media_type": "Text",
    "index_reference": "51004002",
    "language": "por",
    "content": "<p>com uma mente alerta: O verbo grego por trás desta frase é usado no Novo Testamento para retratar a necessidade de os cristãos estarem vigilantes à luz do retorno de Cristo (<a href=\"https://ref.ly/Matt24:42\">Mt 24.42</a>; <a href=\"https://ref.ly/Matt25:13\">25.13</a>; <a href=\"https://ref.ly/Mark13:35\">Mc 13.35</a>,<a href=\"https://ref.ly/Mark13:37\">37</a>; <a href=\"https://ref.ly/1Thess5:6\">1Ts 5.6</a>; <a href=\"https://ref.ly/Rev3:3\">Ap 3.3</a>; <a href=\"https://ref.ly/Rev16:15\">16.15</a>).</p>",
    "associations": {
      "passage": [
        {
          "start_ref": "51004002",
          "start_ref_usfm": "COL 4:2",
          "end_ref": "51004002",
          "end_ref_usfm": "COL 4:2"
        }
      ],
      "resource": []
    }
  },
  {
    "content_id": 716069,
    "reference_id": 9033,
    "title": "Colossenses 4.2–6",
    "media_type": "Text",
    "index_reference": "51004002-51004006",
    "language": "por",
    "content": "<p>As cartas do Novo Testamento frequentemente terminam com uma exortação à oração, juntamente com pedidos de oração.</p>",
    "associations": {
      "passage": [
        {
          "start_ref": "51004002",
          "start_ref_usfm": "COL 4:2",
          "end_ref": "51004006",
          "end_ref_usfm": "COL 4:6"
        }
      ],
      "resource": []
    }
  },
  {
    "content_id": 716071,
    "reference_id": 9035,
    "title": "Colossenses 4.3",
    "media_type": "Text",
    "index_reference": "51004003",
    "language": "por",
    "content": "<p>que Deus nos conceda muitas oportunidades (literalmente <em>que Deus possa abrir para nós uma porta</em>): Uma porta aberta é uma metáfora para uma oportunidade de proclamar as boas-novas (veja também <a href=\"https://ref.ly/Acts14:27\">At 14.27</a>; <a href=\"https://ref.ly/1Cor16:9\">1Co 16.9</a>; <a href=\"https://ref.ly/2Cor2:12\">2Co 2.12</a>). • seu plano misterioso a respeito de Cristo: Veja <a href=\"https://ref.ly/Col1:26-Col1:27\">Cl 1.26–27</a>; <a href=\"https://ref.ly/Col2:2\">2.2</a>. • É por isso que estou aqui acorrentado: A dedicação de Paulo à pregação das boas-novas levou à sua prisão (veja <span data-bnType=\"resourceReference\" data-resourceId=\"Col_BookIntro_Filament\" data-resourceType=\"TyndaleStudyNotes\">Introdução ao Livro de Colossenses</span>, “Data e Ocasião da Escrita”).</p>",
    "associations": {
      "passage": [
        {
          "start_ref": "51004003",
          "start_ref_usfm": "COL 4:3",
          "end_ref": "51004003",
          "end_ref_usfm": "COL 4:3"
        }
      ],
      "resource": [
        {
          "reference_id": 26427,
          "content_id": 639550,
          "resource_code": "Unknown",
          "label": "Colossenses",
          "language": "por"
        }
      ]
    }
  },
  {
    "content_id": 716072,
    "reference_id": 9036,
    "title": "Colossenses 4.5",
    "media_type": "Text",
    "index_reference": "51004005",
    "language": "por",
    "content": "<p>Aproveite ao máximo cada oportunidade (literalmente <em>compre o tempo</em>): Assim como pessoas que compram um produto oferecido a um bom preço, os cristãos devem &quot;comprar&quot; cada oportunidade que Deus lhes dá para compartilhar as boas-novas e servir aos outros.</p>",
    "associations": {
      "passage": [
        {
          "start_ref": "51004005",
          "start_ref_usfm": "COL 4:5",
          "end_ref": "51004005",
          "end_ref_usfm": "COL 4:5"
        }
      ],
      "resource": []
    }
  },
  {
    "content_id": 716073,
    "reference_id": 9037,
    "title": "Colossenses 4.6",
    "media_type": "Text",
    "index_reference": "51004006",
    "language": "por",
    "content": "<p>atraente (literalmente <em>temperado com sal</em>): O sal é tanto um tempero quanto um conservante (veja <a href=\"https://ref.ly/Matt5:13\">Mt 5.13</a>). Paulo pode estar incentivando os cristãos a falarem com os descrentes usando palavras bem escolhidas e cativantes. Os rabinos ocasionalmente se referiam à sabedoria como <em>sal,</em> então Paulo também pode estar exortando os cristãos a falarem com sabedoria.</p>",
    "associations": {
      "passage": [
        {
          "start_ref": "51004006",
          "start_ref_usfm": "COL 4:6",
          "end_ref": "51004006",
          "end_ref_usfm": "COL 4:6"
        }
      ],
      "resource": []
    }
  },
  {
    "content_id": 716075,
    "reference_id": 9039,
    "title": "Colossenses 4.7",
    "media_type": "Text",
    "index_reference": "51004007",
    "language": "por",
    "content": "<p>Tíquico era da província da Ásia, onde Colossos estava localizada (<a href=\"https://ref.ly/Acts20:4\">At 20.4</a>). Ele trabalhou com Paulo especialmente nessa província (<a href=\"https://ref.ly/Eph6:21\">Ef 6.21</a>; <a href=\"https://ref.ly/2Tim4:12\">2Tm 4.12</a>). Mais tarde, ele foi enviado para trabalhar com Tito em Creta (<a href=\"https://ref.ly/Titus3:12\">Tt 3.12</a>). Tíquico provavelmente levou esta carta junto com as cartas conhecidas como Efésios e Filemom.</p>",
    "associations": {
      "passage": [
        {
          "start_ref": "51004007",
          "start_ref_usfm": "COL 4:7",
          "end_ref": "51004007",
          "end_ref_usfm": "COL 4:7"
        }
      ],
      "resource": []
    }
  },
  {
    "content_id": 716074,
    "reference_id": 9038,
    "title": "Colossenses 4.7–18",
    "media_type": "Text",
    "index_reference": "51004007-51004018",
    "language": "por",
    "content": "<p>A maioria das cartas do Novo Testamento termina com uma série de saudações e referências a colaboradores e planos de viagem, mas esta parte de colossenses é mais longa do que o habitual. Paulo, por não poder viajar, pode ter buscado garantir que os colossenses mantivessem conexões com seus colaboradores. Isso os ajudaria a não sucumbir às tentações dos falsos mestres.</p>",
    "associations": {
      "passage": [
        {
          "start_ref": "51004007",
          "start_ref_usfm": "COL 4:7",
          "end_ref": "51004018",
          "end_ref_usfm": "COL 4:18"
        }
      ],
      "resource": []
    }
  },
  {
    "content_id": 716076,
    "reference_id": 9040,
    "title": "Colossenses 4.9",
    "media_type": "Text",
    "index_reference": "51004009",
    "language": "por",
    "content": "<p>Onésimo era um escravo fugitivo que Paulo enviou de volta ao seu mestre, Filemom (veja o <a href=\"https://ref.ly/Phlm1:1-Phlm1:25\">livro de Filemom</a>).</p>",
    "associations": {
      "passage": [
        {
          "start_ref": "51004009",
          "start_ref_usfm": "COL 4:9",
          "end_ref": "51004009",
          "end_ref_usfm": "COL 4:9"
        }
      ],
      "resource": []
    }
  },
  {
    "content_id": 716060,
    "reference_id": 9024,
    "title": "Colossenses 4.10",
    "media_type": "Text",
    "index_reference": "51004010",
    "language": "por",
    "content": "<p>Aristarco era um nome comum, mas ele provavelmente era o mesmo homem de Tessalônica (<a href=\"https://ref.ly/Acts19:29\">At 19.29</a>; <a href=\"https://ref.ly/Acts20:4\">20.4</a>) que acompanhou Paulo em sua viagem a Roma (<a href=\"https://ref.ly/Acts27:2\">At 27.2</a>). Atos não sugere que <em>Aristarco</em> também estava preso, então talvez ele estivesse na prisão com Paulo voluntariamente, compartilhando seu confinamento para encorajá-lo e ajudá-lo no ministério. • Marcos, primo de Barnabé, havia ido com Barnabé e Paulo em sua primeira viagem missionária, mas os deixou antes que a viagem fosse concluída (<a href=\"https://ref.ly/Acts13:13\">At 13.13</a>). Essa deserção levou a uma separação entre Paulo e Barnabé quando a segunda viagem estava prestes a começar (<a href=\"https://ref.ly/Acts15:37-Acts15:40\">At 15.37–40</a>). Paulo e Marcos aparentemente agora estavam reconciliados (veja também <a href=\"https://ref.ly/2Tim4:11\">2Tm 4.11</a>; <a href=\"https://ref.ly/Phlm1:24\">Fm 1.24</a>). • Como você foi instruído antes: Não há outro registro dessa comunicação.</p>",
    "associations": {
      "passage": [
        {
          "start_ref": "51004010",
          "start_ref_usfm": "COL 4:10",
          "end_ref": "51004010",
          "end_ref_usfm": "COL 4:10"
        }
      ],
      "resource": []
    }
  },
  {
    "content_id": 716059,
    "reference_id": 9023,
    "title": "Colossenses 4.10–14",
    "media_type": "Text",
    "index_reference": "51004010-51004014",
    "language": "por",
    "content": "<p>Das seis pessoas mencionadas, cinco também são citadas em <a href=\"https://ref.ly/Phlm1:23-Phlm1:24\">Fm 1.23–24</a>.</p>",
    "associations": {
      "passage": [
        {
          "start_ref": "51004010",
          "start_ref_usfm": "COL 4:10",
          "end_ref": "51004014",
          "end_ref_usfm": "COL 4:14"
        }
      ],
      "resource": []
    }
  },
  {
    "content_id": 716061,
    "reference_id": 9025,
    "title": "Colossenses 4.11",
    "media_type": "Text",
    "index_reference": "51004011",
    "language": "por",
    "content": "<p>Jesus (aquele que chamamos de Justo) é mencionado apenas aqui no Novo Testamento. O sobrenome <em>Justo</em> é incluído porque <em>Jesus</em> (que significa <em>o Senhor salva</em>) era um nome comum entre os judeus do primeiro século.</p>",
    "associations": {
      "passage": [
        {
          "start_ref": "51004011",
          "start_ref_usfm": "COL 4:11",
          "end_ref": "51004011",
          "end_ref_usfm": "COL 4:11"
        }
      ],
      "resource": []
    }
  },
  {
    "content_id": 716062,
    "reference_id": 9026,
    "title": "Colossenses 4.13",
    "media_type": "Text",
    "index_reference": "51004013",
    "language": "por",
    "content": "<p>Laodiceia e Hierápolis eram as duas cidades mais importantes no vale do rio Lico. O fato de Epafras ter orado pelos crentes em Colossos e nessas cidades próximas sugere que ele foi o evangelista pioneiro em todas as três cidades.</p>",
    "associations": {
      "passage": [
        {
          "start_ref": "51004013",
          "start_ref_usfm": "COL 4:13",
          "end_ref": "51004013",
          "end_ref_usfm": "COL 4:13"
        }
      ],
      "resource": []
    }
  },
  {
    "content_id": 716063,
    "reference_id": 9027,
    "title": "Colossenses 4.14",
    "media_type": "Text",
    "index_reference": "51004014",
    "language": "por",
    "content": "<p>Lucas, o amado médico, é bem conhecido como o autor de Atos e do Evangelho que leva seu nome. Este versículo é a única evidência para dois fatos sobre Lucas: ele era médico e não era um crente judeu (veja <a href=\"https://ref.ly/Col4:10-Col4:11\">Cl 4.10–11</a>). • Em contraste com as outras pessoas mencionadas nesta passagem, nenhum detalhe é dado sobre Demas. Talvez Paulo não o conhecesse bem. Demas mais tarde abandonou Paulo (<a href=\"https://ref.ly/2Tim4:10\">2Tm 4.10</a>).</p>",
    "associations": {
      "passage": [
        {
          "start_ref": "51004014",
          "start_ref_usfm": "COL 4:14",
          "end_ref": "51004014",
          "end_ref_usfm": "COL 4:14"
        }
      ],
      "resource": []
    }
  },
  {
    "content_id": 716064,
    "reference_id": 9028,
    "title": "Colossenses 4.15",
    "media_type": "Text",
    "index_reference": "51004015",
    "language": "por",
    "content": "<p>Ninfa e a igreja que se reúne em sua casa: Nos primeiros dois séculos da igreja cristã, quase todos os crentes se reuniam para adorar em casas particulares. Não se sabe mais nada sobre Ninfa.</p>",
    "associations": {
      "passage": [
        {
          "start_ref": "51004015",
          "start_ref_usfm": "COL 4:15",
          "end_ref": "51004015",
          "end_ref_usfm": "COL 4:15"
        }
      ],
      "resource": []
    }
  },
  {
    "content_id": 716065,
    "reference_id": 9029,
    "title": "Colossenses 4.16",
    "media_type": "Text",
    "index_reference": "51004016",
    "language": "por",
    "content": "<p>Você deve ler a carta que escrevi para eles: várias tentativas foram feitas ao longo dos anos para identificar a carta aos Laodicenses com uma carta ou fragmento do Novo Testamento, mas é mais provável que a carta de Paulo à igreja de Laodiceia tenha sido perdida.</p>",
    "associations": {
      "passage": [
        {
          "start_ref": "51004016",
          "start_ref_usfm": "COL 4:16",
          "end_ref": "51004016",
          "end_ref_usfm": "COL 4:16"
        }
      ],
      "resource": []
    }
  },
  {
    "content_id": 716066,
    "reference_id": 9030,
    "title": "Colossenses 4.17",
    "media_type": "Text",
    "index_reference": "51004017",
    "language": "por",
    "content": "<p>Arquipo: Veja também <a href=\"https://ref.ly/Phlm1:2\">Fm 1.2</a>. Não temos como saber mais sobre o ministério que o Senhor lhe deu.</p>",
    "associations": {
      "passage": [
        {
          "start_ref": "51004017",
          "start_ref_usfm": "COL 4:17",
          "end_ref": "51004017",
          "end_ref_usfm": "COL 4:17"
        }
      ],
      "resource": []
    }
  },
  {
    "content_id": 716067,
    "reference_id": 9031,
    "title": "Colossenses 4.18",
    "media_type": "Text",
    "index_reference": "51004018",
    "language": "por",
    "content": "<p>Aqui está minha saudação de minha própria mão — Paulo: Como a maioria das cartas antigas, colossenses provavelmente foi ditada por Paulo a um escriba, ou <em>amanuense,</em> que teria sido treinado para escrever de forma clara e compacta. Para autenticar a carta, Paulo adicionou sua própria saudação manuscrita no final (cp. comentário de Paulo em <a href=\"https://ref.ly/2Thess2:2\">2 Tessalonicenses 2.2</a>).</p>",
    "associations": {
      "passage": [
        {
          "start_ref": "51004018",
          "start_ref_usfm": "COL 4:18",
          "end_ref": "51004018",
          "end_ref_usfm": "COL 4:18"
        }
      ],
      "resource": []
    }
  }
]